<?xml version="1.0" encoding="UTF-8"?>
<objects serializationModel="Studio.02.03.00">
	<object class="AudioFile" id="{669d6a21-ece7-4126-8b36-228196657d93}">
		<property name="assetPath">
			<value>SFX/PPporta.wav</value>
		</property>
		<property name="frequencyInKHz">
			<value>48</value>
		</property>
		<property name="channelCount">
			<value>1</value>
		</property>
		<property name="length">
			<value>1.7890833333333334</value>
		</property>
		<relationship name="masterAssetFolder">
			<destination>{808c1b10-9e3d-49a3-9d33-fcd6d8e069f9}</destination>
		</relationship>
	</object>
</objects>
